akreceive/__init__.py
akreceive/core.py
akreceiver-0.1.0.dist-info/METADATA
akreceiver-0.1.0.dist-info/WHEEL
akreceiver-0.1.0.dist-info/top_level.txt
akreceiver-0.1.0.dist-info/RECORD
