Metadata-Version: 2.4
Name: akreceiver
Version: 0.1.0
Summary: A simple file receiver that reads last line and clears the file.
Author: Akshay Ajit Bhawar
Requires-Python: >=3.6
Dynamic: author
Dynamic: requires-python
Dynamic: summary
